SRCNN/model.py
SRCNN/solver.py
sr_model_2025_SRCNN/__init__.py
sr_model_2025_SRCNN/__main__.py
sr_model_2025_SRCNN/super_resolution_model.py
sr_model_2025_SRCNN/SRCNN/model.py
sr_model_2025_SRCNN/SRCNN/solver.py
srm/__init__.py
srm/__main__.py
srm/super_resolution_model.py
srm/SRCNN/model.py
srm/SRCNN/solver.py
sr_model_2025_srcnn-0.1.3.dist-info/METADATA
sr_model_2025_srcnn-0.1.3.dist-info/WHEEL
sr_model_2025_srcnn-0.1.3.dist-info/entry_points.txt
sr_model_2025_srcnn-0.1.3.dist-info/top_level.txt
sr_model_2025_srcnn-0.1.3.dist-info/RECORD
