Metadata-Version: 2.4
Name: sr_model_2025_SRCNN
Version: 0.1.3
Summary: Test project
Author: Носкова Екатерина
Author-email: Noskova Ekaterina <test@test.ru>
Classifier: Environment :: Console
Classifier: Intended Audience :: Developers
Classifier: Intended Audience :: Information Technology
Classifier: Intended Audience :: System Administrators
Classifier: Natural Language :: English
Classifier: Operating System :: POSIX
Classifier: Programming Language :: Python :: 3
Classifier: Programming Language :: Python :: 3.11
Classifier: Programming Language :: Python :: 3.12
Classifier: Programming Language :: Python :: 3.13
Classifier: Programming Language :: Python :: 3 :: Only
Classifier: Topic :: System :: Installation/Setup
Classifier: Topic :: System :: Systems Administration
Classifier: Topic :: Utilities
Requires-Python: >=3.11
Requires-Dist: torch
Requires-Dist: requests
Requires-Dist: torchvision
Requires-Dist: pillow
Dynamic: author
